randomly_change_self/__init__.py
randomly_change_self/change_self.py
randomly_change_self-0.2.0.dist-info/LICENSE
randomly_change_self-0.2.0.dist-info/METADATA
randomly_change_self-0.2.0.dist-info/WHEEL
randomly_change_self-0.2.0.dist-info/entry_points.txt
randomly_change_self-0.2.0.dist-info/RECORD
