Metadata-Version: 2.1
Name: randomly-change-self
Version: 0.2.0
Summary: Change all instances of `self` to `this` in one randomly chosen scope
Home-page: https://github.com/sco1/
Author: sco1
Author-email: sco1.git@gmail.com
Requires-Python: >=3.10,<4.0
Classifier: Development Status :: 4 - Beta
Classifier: Intended Audience :: Developers
Classifier: License :: OSI Approved :: MIT License
Classifier: Operating System :: OS Independent
Classifier: Programming Language :: Python :: 3
Classifier: Programming Language :: Python :: 3.10
Classifier: Programming Language :: Python :: 3.11
Classifier: Programming Language :: Python :: 3.12
Classifier: Programming Language :: Python :: 3 :: Only
Classifier: Programming Language :: Python :: 3.13
Classifier: Typing :: Typed
Requires-Dist: tokenize-rt (>=5.2,<6.0)
Project-URL: Repository, https://github.com/sco1/randomly-change-self
